{
  "project_info": {
    "project_number": "178190282027",
    "project_id": "dpp-app-59cc4",
    "storage_bucket": "dpp-app-59cc4.appspot.com"
  },
  "client": [
    {
      "client_info": {
        "mobilesdk_app_id": "1:178190282027:android:bbdfc0179545adf174696e",
        "android_client_info": {
          "package_name": "com.example.dpp"
        }
      },
      "oauth_client": [
        {
          "client_id": "178190282027-qgpkhfc3i3g8vri83vekihqccee40i83.apps.googleusercontent.com",
          "client_type": 3
        }
      ],
      "api_key": [
        {
          "current_key": "AIzaSyDEzj-B26YXsYQscB-yKTXOhmgarcyVgPA"
        }
      ],
      "services": {
        "appinvite_service": {
          "other_platform_oauth_client": [
            {
              "client_id": "178190282027-qgpkhfc3i3g8vri83vekihqccee40i83.apps.googleusercontent.com",
              "client_type": 3
            }
          ]
        }
      }
    }
  ],
  "configuration_version": "1"
}